setup.py
django_template_names.egg-info/PKG-INFO
django_template_names.egg-info/SOURCES.txt
django_template_names.egg-info/dependency_links.txt
django_template_names.egg-info/pbr.json
django_template_names.egg-info/top_level.txt
template_names/__init__.py