Metadata-Version: 1.1
Name: django-template-names
Version: 0.2.1
Summary: Django templates names list automatic helper
Home-page: https://github.com/phpdude/django-template-names
Author: Alexandr I. Shurigin
Author-email: ya@helldude.ru
License: UNKNOWN
Platform: UNKNOWN
Classifier: Framework :: Django
Classifier: Operating System :: OS Independent
Classifier: Topic :: Software Development
